connector.py
diagram.py
drawing.py
main.py
nodeBase.py
onode.py
utils/diagramUtils.py
utils/objectUtils.py
colelmen_drawio_parser-0.0.1.dist-info/METADATA
colelmen_drawio_parser-0.0.1.dist-info/WHEEL
colelmen_drawio_parser-0.0.1.dist-info/top_level.txt
colelmen_drawio_parser-0.0.1.dist-info/RECORD
