Metadata-Version: 2.1
Name: colelmen-drawio-parser
Version: 0.0.1
Summary: DrawioParser
Home-page: UNKNOWN
Author: Colemen Atwood
Author-email: <atwoodcolemen@gmail.com>
License: UNKNOWN
Keywords: python
Platform: UNKNOWN
Classifier: Development Status :: 3 - Alpha
Classifier: Intended Audience :: Education
Classifier: Programming Language :: Python :: 2
Classifier: Programming Language :: Python :: 3
Classifier: Operating System :: MacOS :: MacOS X
Classifier: Operating System :: Microsoft :: Windows
Requires-Dist: colemen-file-utils
Requires-Dist: colemen-string-utils
Requires-Dist: lxml
